LICENSE.txt
MANIFEST.in
setup.cfg
setup.py
zanpakuto/__init__.py
zanpakuto/cleaners.py
zanpakuto/utils.py
zanpakuto.egg-info/PKG-INFO
zanpakuto.egg-info/SOURCES.txt
zanpakuto.egg-info/dependency_links.txt
zanpakuto.egg-info/requires.txt
zanpakuto.egg-info/top_level.txt