Metadata-Version: 1.1
Name: zanpakuto
Version: 0.2
Summary: A small utility to simplify HTML excerpts
Home-page: https://github.com/amferraz/zanpakuto
Author: Anderson Ferraz
Author-email: amarquesferraz@gmail.com
License: UNKNOWN
Download-URL: https://github.com/amferraz/zanpakuto/archive/0.2.zip
Platform: UNKNOWN
